seededitorqt/__init__.py
seededitorqt/plugin.py
seededitorqt/seed_editor_qt.py
seededitorqt-2.1.4.dist-info/licenses/LICENSE
seededitorqt-2.1.4.dist-info/METADATA
seededitorqt-2.1.4.dist-info/WHEEL
seededitorqt-2.1.4.dist-info/top_level.txt
seededitorqt-2.1.4.dist-info/RECORD
